resqml22dev3/__init__.py
resqml22dev3/absolute_pressure.py
resqml22dev3/absorbed_dose_measure.py
resqml22dev3/absorbed_dose_measure_ext.py
resqml22dev3/absorbed_dose_uom.py
resqml22dev3/abstract_activity_parameter.py
resqml22dev3/abstract_boolean_array.py
resqml22dev3/abstract_column_layer_grid_geometry.py
resqml22dev3/abstract_column_layer_grid_representation.py
resqml22dev3/abstract_contact_interpretation_part.py
resqml22dev3/abstract_contact_representation_part.py
resqml22dev3/abstract_contextual_object.py
resqml22dev3/abstract_coordinate_operation_type.py
resqml22dev3/abstract_coordinate_system_type.py
resqml22dev3/abstract_data_object.py
resqml22dev3/abstract_dq_element_type.py
resqml22dev3/abstract_dq_positional_accuracy_type.py
resqml22dev3/abstract_dq_result_type.py
resqml22dev3/abstract_ex_geographic_extent_type.py
resqml22dev3/abstract_feature.py
resqml22dev3/abstract_feature_interpretation.py
resqml22dev3/abstract_floating_point_array.py
resqml22dev3/abstract_general_conversion_type.py
resqml22dev3/abstract_geodetic_crs.py
resqml22dev3/abstract_geometry.py
resqml22dev3/abstract_gmltype.py
resqml22dev3/abstract_graphical_information.py
resqml22dev3/abstract_graphical_information_for_indexable_element.py
resqml22dev3/abstract_grid_geometry.py
resqml22dev3/abstract_grid_representation.py
resqml22dev3/abstract_integer_array.py
resqml22dev3/abstract_local3d_crs.py
resqml22dev3/abstract_numeric_array.py
resqml22dev3/abstract_object.py
resqml22dev3/abstract_object_type.py
resqml22dev3/abstract_organization_interpretation.py
resqml22dev3/abstract_parameter_key.py
resqml22dev3/abstract_parametric_line_array.py
resqml22dev3/abstract_parametric_line_geometry.py
resqml22dev3/abstract_parent_window.py
resqml22dev3/abstract_plane_geometry.py
resqml22dev3/abstract_point3d_array.py
resqml22dev3/abstract_pressure_value.py
resqml22dev3/abstract_projected_crs.py
resqml22dev3/abstract_property.py
resqml22dev3/abstract_property_lookup.py
resqml22dev3-1.0.0.dist-info/LICENSE
resqml22dev3-1.0.0.dist-info/WHEEL
resqml22dev3-1.0.0.dist-info/METADATA
resqml22dev3-1.0.0.dist-info/RECORD
